pms_furiosa_processor/__init__.py
pms_furiosa_processor/_const.py
pms_furiosa_processor/_dpir_processor.py
pms_furiosa_processor/_dru_rbpn_sr_f3_processor.py
pms_furiosa_processor-1.1.0.dist-info/METADATA
pms_furiosa_processor-1.1.0.dist-info/WHEEL
pms_furiosa_processor-1.1.0.dist-info/RECORD
